azure_servicebus_cli/__init__.py
azure_servicebus_cli/cli.py
azure_servicebus_cli-0.1.2.dist-info/LICENSE
azure_servicebus_cli-0.1.2.dist-info/METADATA
azure_servicebus_cli-0.1.2.dist-info/WHEEL
azure_servicebus_cli-0.1.2.dist-info/entry_points.txt
azure_servicebus_cli-0.1.2.dist-info/top_level.txt
azure_servicebus_cli-0.1.2.dist-info/RECORD
