Metadata-Version: 2.1
Name: azure-servicebus-cli
Version: 0.1.2
Summary: A CLI tool for interacting with Azure Service Bus Queues
Home-page: https://github.com/yourusername/azure-servicebus-cli
Author: Mustafa Hakimi
Author-email: mustafa.hakimi94@gmail.com
Classifier: Programming Language :: Python :: 3
Classifier: License :: OSI Approved :: MIT License
Classifier: Operating System :: OS Independent
Requires-Python: >=3.7
License-File: LICENSE
Requires-Dist: azure-servicebus>=7.0.0
